student_46165/init.py
student_46165/saylani.py
student_46165-0.2.dist-info/METADATA
student_46165-0.2.dist-info/WHEEL
student_46165-0.2.dist-info/top_level.txt
student_46165-0.2.dist-info/RECORD
