Metadata-Version: 2.1
Name: student-46165
Version: 0.2
Summary: This is the Saylani DB Package
Author: Shahzad Ahmed Khan
License: UNKNOWN
Platform: UNKNOWN
